textjenerator/config.py
textjenerator/core/text_generator.py
textjenerator/examples/generate_text.py
textjenerator/examples/split_workflow.py
textjenerator/models/__init__.py
textjenerator/models/llama_cpp.py
textjenerator/models/registry.py
textjenerator-1.0.1.dist-info/METADATA
textjenerator-1.0.1.dist-info/WHEEL
textjenerator-1.0.1.dist-info/licenses/LICENSE
textjenerator-1.0.1.dist-info/RECORD
