Metadata-Version: 2.4
Name: textjenerator
Version: 1.0.1
Summary: AI text generator
License-Expression: MIT
License-File: LICENSE
Author: Warren Davies
Requires-Python: >=3.10,<3.15
Classifier: Programming Language :: Python :: 3
Classifier: Programming Language :: Python :: 3.12
Classifier: License :: OSI Approved :: MIT License
Classifier: Operating System :: OS Independent
Classifier: Topic :: Scientific/Engineering :: Artificial Intelligence
Requires-Dist: llama-cpp-python (>=0.3.16,<0.4.0)
Requires-Dist: torch (>=2.9.1,<3.0.0)
